[
    {
        "id": "425544bb29f9315cb4244b3fcd92c05fca29e0bc2d83ec418706a5f53fbeeac5-1",
        "text": "2024-2028 Domeniul Inginerie Industriala | Inginerie integrată (Lb. Engleza) Tehnologia constructiilor de masini Tehnologia constructiilor de masini (DUAL) Informatica aplicată în inginerie industrială Ingineria si managementul calitatii | Domeniul Inginerie si Management | | Domeniul Mecatronica si Robotica | | Domeniul Științe Ingineresti Aplicate | | Domeniul Inginerie Mecanică | 2023-2027 Domeniul Inginerie Industriala | Industrial Engineering (Lb. Engleza) Tehnologia constructiilor de masini Informatica aplicată în inginerie industrială Ingineria si managementul calitatii | Domeniul Inginerie si Management | | Domeniul Mecatronica si Robotica | | Domeniul Științe Ingineresti Aplicate | | Domeniul Inginerie Mecanică | 2022-2026 Domeniul Inginerie Industriala | Industrial Engineering (Lb. Engleza) Tehnologia constructiilor de masini Informatica aplicată în inginerie industrială Ingineria si managementul calitatii | Domeniul Inginerie si Management | | Domeniul Mecatronica si Robotica | | Domeniul Științe Ingineresti Aplicate | | Domeniul Inginerie Mecanică | 2021-2025 Domeniul Inginerie Industriala | Industrial Engineering (Lb. Engleza) Tehnologia constructiilor de masini Informatica aplicată în inginerie industrială Ingineria si managementul calitatii Ingineria securitatii in industrie Tehnologii Industriale Inteligente | Domeniul Inginerie si Management | | Domeniul Mecatronica si Robotica | | Domeniul Științe Ingineresti Aplicate |",
        "url": "https://www.fiir.upb.ro/index.php/ro/licenta/planuri-de-invatamant",
        "type": "txt",
        "filename": "index.php_ro_licenta_planuri-de-invatamant.txt",
        "page_number": null,
        "table_id": null,
        "table_text": null
    }
]